ex01/Programming_task_1/halfadder.sv
module halfadder (
  input logic a, b,
  output logic s, c
);

  assign s = a ^ b;
  assign c = a & b;

endmodule

ex01/Programming_task_1/fulladder.sv
`include "halfadder.sv"

module fulladder(
  input logic a, b, c_in,
  output logic s, c_out
);

wire sum1, carry1, carry2;

halfadder first ( a, b, sum1, carry1);
halfadder second(sum1, c_in, s, carry2);

or carryOr(c_out, carry1, carry2);

endmodule

ex01/Programming_task_3/and.sv
module and_gate(
  input logic a, b,
  output logic o
);

  assign o = a & b;

endmodule

ex01/Programming_task_3/mult.sv
`include "and.sv"
`include "fulladder.sv"

module mult(
  input  logic a0, a1, a2, b0, b1, b2,
  output logic s0, s1, s2, s3, s4, s5
);

// Partial products for 1st bit of B
// ppBA (bit B from B, bit A from A)
and_gate and1 (b0, a0, pp_00);
and_gate and2 (b0, a1, pp_01);
and_gate and3 (b0, a2, pp_02);

// Partial products for 2nd bit of B
and_gate and4 (b1, a0, pp_10);
and_gate and5 (b1, a1, pp_11);
and_gate and6 (b1, a2, pp_12);

// Partial products for 3rd bit of B
and_gate and7 (b2, a0, pp_20);
and_gate and8 (b2, a1, pp_21);
and_gate and9 (b2, a2, pp_22);

// buf(out, in) just propagates the same value
buf(s0, a0);

// Summations: Row 1
// Full-Adder names: fXY (X=row, Y=number of the adder from left)
fulladder f11 (
  .a(pp_01),
  .b(pp_10),
  .c_in(0),
  .s(s1),
  .c_out(carry_for_f12)
);

fulladder f12 (
  .a(pp_02),
  .b(pp_11),
  .c_in(carry_for_f12),
  .s(sum_for_f21),
  .c_out(carry_for_f13)
);

fulladder f13 (
  .a(pp_12),
  .b(0),
  .c_in(0),
  .s(sum_for_f22),
  .c_out(b_for_f23)
);

// Row 2
fulladder f21 (
  .a(pp_20),
  .b(sum_for_f21),
  .c_in(0),
  .s(s2),
  .c_out(carry_for_f22)
);

fulladder f22 (
  .a(pp_21),
  .b(sum_for_f22),
  .c_in(carry_for_f22),
  .s(s3),
  .c_out(carry_for_f23)
);

fulladder f23 (
  .a(pp_22),
  .b(b_for_f23),
  .c_in(carry_for_f23),
  .s(s4),
  .c_out(s5)
);

endmodule

ex01/vcd_files/mult.vcd
$date
    May  8, 2025  11:06:28
$end
$comment
	SimVision SST: d37fa0eb34ee6115b71f12b7fe0b461f
$end
$version
    TOOL:	xmsim(64)	22.09-s007
$end
$timescale
    1 fs
$end

$scope module mult $end
$var wire      1 !    a0  $end
$var wire      1 "    a1  $end
$var wire      1 #    a2  $end
$var wire      1 $    b0  $end
$var wire      1 %    b1  $end
$var wire      1 &    b2  $end
$var reg       1 '    s0 $end
$var reg       1 (    s1 $end
$var reg       1 )    s2 $end
$var reg       1 *    s3 $end
$var reg       1 +    s4 $end
$var reg       1 ,    s5 $end
$var wire      1 -    pp_00  $end
$var wire      1 .    pp_01  $end
$var wire      1 /    pp_02  $end
$var wire      1 0    pp_10  $end
$var wire      1 1    pp_11  $end
$var wire      1 2    pp_12  $end
$var wire      1 3    pp_20  $end
$var wire      1 4    pp_21  $end
$var wire      1 5    pp_22  $end
$var wire      1 6    carry_for_f12  $end
$var wire      1 7    carry_for_f13  $end
$var wire      1 8    sum_for_f21  $end
$var wire      1 9    b_for_f23  $end
$var wire      1 :    sum_for_f22  $end
$var wire      1 ;    carry_for_f22  $end
$var wire      1 <    carry_for_f23  $end

$scope module and1 $end
$var wire      1 $    a  $end
$var wire      1 !    b  $end
$var reg       1 =    o $end
$upscope $end


$scope module and2 $end
$var wire      1 $    a  $end
$var wire      1 "    b  $end
$var reg       1 >    o $end
$upscope $end


$scope module and3 $end
$var wire      1 $    a  $end
$var wire      1 #    b  $end
$var reg       1 ?    o $end
$upscope $end


$scope module and4 $end
$var wire      1 %    a  $end
$var wire      1 !    b  $end
$var reg       1 @    o $end
$upscope $end


$scope module and5 $end
$var wire      1 %    a  $end
$var wire      1 "    b  $end
$var reg       1 A    o $end
$upscope $end


$scope module and6 $end
$var wire      1 %    a  $end
$var wire      1 #    b  $end
$var reg       1 B    o $end
$upscope $end


$scope module and7 $end
$var wire      1 &    a  $end
$var wire      1 !    b  $end
$var reg       1 C    o $end
$upscope $end


$scope module and8 $end
$var wire      1 &    a  $end
$var wire      1 "    b  $end
$var reg       1 D    o $end
$upscope $end


$scope module and9 $end
$var wire      1 &    a  $end
$var wire      1 #    b  $end
$var reg       1 E    o $end
$upscope $end


$scope module f11 $end
$var wire      1 .    a  $end
$var wire      1 0    b  $end
$var wire      1 F    c_in  $end
$var reg       1 G    s $end
$var reg       1 H    c_out $end
$var wire      1 I    sum1  $end
$var wire      1 J    carry1  $end
$var wire      1 K    carry2  $end

$scope module first $end
$var wire      1 .    a  $end
$var wire      1 0    b  $end
$var reg       1 L    s $end
$var reg       1 M    c $end
$upscope $end


$scope module second $end
$var wire      1 I    a  $end
$var wire      1 F    b  $end
$var reg       1 N    s $end
$var reg       1 O    c $end
$upscope $end

$upscope $end


$scope module f12 $end
$var wire      1 /    a  $end
$var wire      1 1    b  $end
$var wire      1 6    c_in  $end
$var reg       1 P    s $end
$var reg       1 Q    c_out $end
$var wire      1 R    sum1  $end
$var wire      1 S    carry1  $end
$var wire      1 T    carry2  $end

$scope module first $end
$var wire      1 /    a  $end
$var wire      1 1    b  $end
$var reg       1 U    s $end
$var reg       1 V    c $end
$upscope $end


$scope module second $end
$var wire      1 R    a  $end
$var wire      1 6    b  $end
$var reg       1 W    s $end
$var reg       1 X    c $end
$upscope $end

$upscope $end


$scope module f13 $end
$var wire      1 2    a  $end
$var wire      1 Y    b  $end
$var wire      1 7    c_in  $end
$var reg       1 Z    s $end
$var reg       1 [    c_out $end
$var wire      1 \    sum1  $end
$var wire      1 ]    carry1  $end
$var wire      1 ^    carry2  $end

$scope module first $end
$var wire      1 2    a  $end
$var wire      1 Y    b  $end
$var reg       1 _    s $end
$var reg       1 `    c $end
$upscope $end


$scope module second $end
$var wire      1 \    a  $end
$var wire      1 7    b  $end
$var reg       1 a    s $end
$var reg       1 b    c $end
$upscope $end

$upscope $end


$scope module f21 $end
$var wire      1 3    a  $end
$var wire      1 8    b  $end
$var wire      1 c    c_in  $end
$var reg       1 d    s $end
$var reg       1 e    c_out $end
$var wire      1 f    sum1  $end
$var wire      1 g    carry1  $end
$var wire      1 h    carry2  $end

$scope module first $end
$var wire      1 3    a  $end
$var wire      1 8    b  $end
$var reg       1 i    s $end
$var reg       1 j    c $end
$upscope $end


$scope module second $end
$var wire      1 f    a  $end
$var wire      1 c    b  $end
$var reg       1 k    s $end
$var reg       1 l    c $end
$upscope $end

$upscope $end


$scope module f22 $end
$var wire      1 4    a  $end
$var wire      1 :    b  $end
$var wire      1 ;    c_in  $end
$var reg       1 m    s $end
$var reg       1 n    c_out $end
$var wire      1 o    sum1  $end
$var wire      1 p    carry1  $end
$var wire      1 q    carry2  $end

$scope module first $end
$var wire      1 4    a  $end
$var wire      1 :    b  $end
$var reg       1 r    s $end
$var reg       1 s    c $end
$upscope $end


$scope module second $end
$var wire      1 o    a  $end
$var wire      1 ;    b  $end
$var reg       1 t    s $end
$var reg       1 u    c $end
$upscope $end

$upscope $end


$scope module f23 $end
$var wire      1 5    a  $end
$var wire      1 9    b  $end
$var wire      1 <    c_in  $end
$var reg       1 v    s $end
$var reg       1 w    c_out $end
$var wire      1 x    sum1  $end
$var wire      1 y    carry1  $end
$var wire      1 z    carry2  $end

$scope module first $end
$var wire      1 5    a  $end
$var wire      1 9    b  $end
$var reg       1 {    s $end
$var reg       1 |    c $end
$upscope $end


$scope module second $end
$var wire      1 x    a  $end
$var wire      1 <    b  $end
$var reg       1 }    s $end
$var reg       1 ~    c $end
$upscope $end

$upscope $end

$upscope $end

$enddefinitions $end
$dumpvars
0!
0"
0#
0$
0%
0&
0'
0(
0)
0*
0+
0,
0-
0.
0/
00
01
02
03
04
05
06
07
08
09
0:
0;
0<
0=
0>
0?
0@
0A
0B
0C
0D
0E
0F
0G
0H
0I
0J
0K
0L
0M
0N
0O
0P
0Q
0R
0S
0T
0U
0V
0W
0X
0Y
0Z
0[
0\
0]
0^
0_
0`
0a
0b
0c
0d
0e
0f
0g
0h
0i
0j
0k
0l
0m
0n
0o
0p
0q
0r
0s
0t
0u
0v
0w
0x
0y
0z
0{
0|
0}
0~
$end
#5000
1$
#10000
0$
1%
#15000
1$
#20000
0$
0%
1&
#25000
1$
#30000
0$
1%
#35000
1$
#40000
1!
0$
0%
0&
#45000
1$
1=
1-
1'
#50000
0$
1%
0=
1@
10
0-
1L
0'
1I
1N
1G
1(
#55000
1$
1=
1-
1'
#60000
0$
0%
1&
0=
0@
1C
13
00
0-
1i
0L
0'
0I
1f
0N
1k
1d
0G
0(
1)
#65000
1$
1=
1-
1'
#70000
0$
1%
0=
1@
10
0-
1L
0'
1I
1N
1G
1(
#75000
1$
1=
1-
1'
#80000
0!
1"
0$
0%
0&
0C
0@
0=
0-
00
03
0L
0i
0'
0f
0I
0k
0N
0G
0d
0)
0(
#85000
1$
1>
1.
1L
1I
1N
1G
1(
#90000
0$
1%
0>
1A
11
0.
1U
0L
0I
1R
0N
1W
1P
0G
18
0(
1i
1f
1k
1d
1)
#95000
1$
1>
1.
1L
1I
1N
1G
1(
#100000
0$
0%
1&
0>
0A
1D
14
01
0.
1r
0U
0L
0I
0R
1o
0N
0W
1t
1m
0P
0G
08
0(
0i
1*
0f
0k
0d
0)
#105000
1$
1>
1.
1L
1I
1N
1G
1(
#110000
0$
1%
0>
1A
11
0.
1U
0L
0I
1R
0N
1W
1P
0G
18
0(
1i
1f
1k
1d
1)
#115000
1$
1>
1.
1L
1I
1N
1G
1(
#120000
1!
0$
0%
0&
0>
0A
0D
04
01
0.
0r
0U
0L
0I
0R
0o
0N
0W
0t
0m
0P
0G
08
0(
0i
0*
0f
0k
0d
0)
#125000
1$
1>
1=
1-
1.
1L
1'
1I
1N
1G
1(
#130000
0$
1%
0>
0=
1A
1@
10
11
0-
0.
1U
0'
1R
1W
1P
18
1i
1f
1k
1d
1)
#135000
1$
1>
1=
1-
1.
0L
1M
1'
1J
0I
0N
1H
16
0W
1X
0G
1T
0(
0P
1Q
17
08
1a
0i
0f
0k
1Z
1:
1r
0d
1o
0)
1t
1m
1*
#140000
0$
0%
1&
0>
0=
0A
0@
1D
1C
13
14
00
01
0-
0.
1i
0r
1s
0M
0U
0'
0R
0J
1p
0o
1f
1W
0X
0t
1k
1n
0H
06
1<
0T
0W
1}
1d
0m
1P
0Q
07
18
0a
0i
1j
0*
1)
1v
0P
08
1g
0f
1i
0j
1+
0k
0Z
1e
1;
0:
0g
1f
1t
1r
0s
0d
1k
0e
0;
0p
1o
1d
0)
1m
0n
0<
0}
1*
1)
0v
0+
#145000
1$
1>
1=
1-
1.
1L
1'
1I
1N
1G
1(
#150000
0$
1%
0>
0=
1A
1@
10
11
0-
0.
1U
0'
1R
1W
1P
18
0i
1j
1g
0f
0k
1e
1;
0t
1u
0d
1q
0)
0m
1n
1<
1}
0*
1v
1+
#155000
1$
1>
1=
1-
1.
0L
1M
1'
1J
0I
0N
1H
16
0W
1X
0G
1T
0(
0P
1Q
17
08
1a
1i
0j
0g
1f
1k
1Z
0e
0;
1:
1t
0u
0r
1s
1d
1p
0o
0q
1)
0t
1m
1*
0m
0*
#160000
0!
0"
1#
0$
0%
0&
0C
0@
0=
0D
0A
0>
0.
01
04
0-
00
03
0M
0U
1r
0s
0i
0'
0f
0p
1o
0R
0J
0k
1t
1W
0X
0H
0n
0<
06
0T
0}
0W
1P
1m
0d
0Q
07
18
0a
0)
1*
1i
0P
0v
08
1f
0+
0i
1k
0Z
0:
0f
0r
1d
0k
0o
0d
1)
0t
0m
0)
0*
#165000
1$
1?
1/
1U
1R
1W
1P
18
1i
1f
1k
1d
1)
#170000
0$
1%
0?
1B
12
0/
1_
0U
0R
1\
0W
1a
1Z
0P
08
1:
0i
1r
1o
0f
1t
0k
0d
1m
1*
0)
#175000
1$
1?
1/
1U
1R
1W
1P
18
1i
1f
1k
1d
1)
#180000
0$
0%
1&
0?
0B
1E
15
02
0/
1{
0_
0U
0R
0\
1x
0W
0a
1}
1v
0Z
0P
08
0:
0i
0r
1+
0o
0f
0t
0k
0d
0m
0*
0)
#185000
1$
1?
1/
1U
1R
1W
1P
18
1i
1f
1k
1d
1)
#190000
0$
1%
0?
1B
12
0/
1_
0U
0R
1\
0W
1a
1Z
0P
08
1:
0i
1r
1o
0f
1t
0k
0d
1m
1*
0)
#195000
1$
1?
1/
1U
1R
1W
1P
18
1i
1f
1k
1d
1)
#200000
1!
0$
0%
0&
0?
0B
0E
05
02
0/
0{
0_
0U
0R
0\
0x
0W
0a
0}
0v
0Z
0P
08
0:
0i
0r
0+
0o
0f
0t
0k
0d
0m
0*
0)
#205000
1$
1?
1=
1-
1/
1U
1'
1R
1W
1P
18
1i
1f
1k
1d
1)
#210000
0$
1%
0?
0=
1B
1@
10
12
0-
0/
1L
1_
0U
0'
0R
1\
1I
0W
1a
1N
1G
1Z
0P
08
1:
0i
1r
1(
1o
0f
1t
0k
0d
1m
1*
0)
#215000
1$
1?
1=
1-
1/
1U
1'
1R
1W
1P
18
1i
1f
1k
1d
1)
#220000
0$
0%
1&
0?
0=
0B
0@
1E
1C
13
15
00
02
0-
0/
0i
1j
1{
0L
0_
0U
0'
0R
0\
0I
1x
1g
0f
0W
0a
0N
1}
0k
1e
1;
0t
1u
0d
1v
0G
0Z
0P
08
0:
1q
1i
0j
0r
0(
1+
0)
0m
1n
1<
0o
0g
1f
0}
1~
0*
1t
0u
1k
0e
0;
0q
1z
0t
1d
1m
0v
1w
0n
0<
1}
0~
1,
0+
1*
1)
0m
0z
0*
1v
0w
0,
1+
#225000
1$
1?
1=
1-
1/
1U
1'
1R
1W
1P
18
0i
1j
1g
0f
0k
1e
1;
1t
0d
0)
1m
1*
#230000
0$
1%
0?
0=
1B
1@
10
12
0-
0/
1L
1_
0U
0'
0R
1\
1I
0W
1a
1N
1G
1Z
0P
08
1:
1i
0j
1r
1(
1o
0g
1f
0t
1u
1k
0e
0;
1q
1t
0u
1d
0m
1n
1<
0q
0}
1~
0*
1)
1m
0n
0<
1z
1}
0~
1*
0v
1w
0z
1,
0+
1v
0w
0,
1+
#235000
1$
1?
1=
1-
1/
1U
1'
1R
1W
1P
18
0i
1j
1g
0f
0k
1e
1;
0t
1u
0d
1q
0)
0m
1n
1<
0}
1~
0*
1z
0v
1w
1,
0+
#240000
0!
1"
0$
0%
0&
0C
0@
0=
0?
0B
0E
05
02
0/
0-
00
03
0{
0_
0U
0L
1i
0j
0'
0g
1f
0I
0R
0\
0x
1k
0N
0W
0a
1}
0~
0e
0;
0z
1t
0u
1v
0Z
0P
0G
1d
0w
08
0:
0q
0,
1)
0(
0i
0r
1+
1m
0n
0<
0o
0f
0}
1*
0t
0k
0d
0m
0v
0+
0*
0)
#245000
1$
1?
1>
1.
1/
1L
1U
1R
1I
1W
1N
1G
1P
18
1i
1(
1f
1k
1d
1)
#250000
0$
1%
0?
0>
1B
1A
11
12
0.
0/
1_
0L
0I
1\
0N
1a
1Z
0G
1:
0(
1r
1o
1t
1m
1*
#255000
1$
1?
1>
1.
1/
1L
0U
1V
1S
0R
1I
0W
1N
1Q
17
0a
1b
1G
0P
08
1^
0i
1(
0Z
1[
19
0:
0f
1{
0r
0k
0o
1x
0d
0t
1}
1v
0m
0)
0*
1+
#260000
0$
0%
1&
0?
0>
0B
0A
1E
1D
14
15
01
02
0.
0/
1r
0{
1|
0V
0_
0L
0I
0\
0S
1y
0x
1o
0N
1a
0b
0}
1t
1w
0Q
07
0^
0a
1,
1m
0v
1Z
0G
0[
09
1:
1{
0|
0(
0r
1s
0+
1*
0Z
0:
1p
0o
0y
1x
1r
0s
0t
1}
0w
1n
1<
0p
1o
0}
1~
0,
1v
0m
1t
0n
0<
1z
1}
0~
1m
0*
1+
0v
1w
0z
1,
0+
1*
1v
0w
0,
1+
#265000
1$
1?
1>
1.
1/
1L
1U
1R
1I
1W
1N
1G
1P
18
1i
1(
1f
1k
1d
1)
#270000
0$
1%
0?
0>
1B
1A
11
12
0.
0/
1_
0L
0I
1\
0N
1a
1Z
0G
1:
0(
0r
1s
1p
0o
0t
1n
1<
0}
1~
0m
1z
0*
0v
1w
1,
0+
#275000
1$
1?
1>
1.
1/
1L
0U
1V
1S
0R
1I
0W
1N
1Q
17
0a
1b
1G
0P
08
1^
0i
1(
0Z
1[
19
0:
0f
0{
1|
1r
0s
0k
0p
1o
1y
0x
0d
1t
1}
0~
0n
0<
0z
0}
1v
1m
0)
1*
1+
0v
0+
#280000
1!
0$
0%
0&
0?
0>
0B
0A
0E
0D
04
05
01
02
0.
0/
0r
1{
0|
0V
0_
0L
0I
0\
0S
0y
1x
0o
0N
1a
0b
1}
0t
0w
0Q
07
0^
0a
0,
0m
1v
1Z
0G
0[
09
1:
0{
0(
1r
1+
0*
0Z
0:
1o
0x
0r
1t
0}
0o
0v
1m
0t
0m
1*
0+
0*
#285000
1$
1?
1>
1=
1-
1.
1/
1L
1U
1'
1R
1I
1W
1N
1G
1P
18
1i
1(
1f
1k
1d
1)
#290000
0$
1%
0?
0>
0=
1B
1A
1@
10
11
12
0-
0.
0/
1_
0'
1\
1a
1Z
1:
1r
1o
1t
1m
1*
#295000
1$
1?
1>
1=
1-
1.
1/
0L
1M
0U
1V
1'
1S
0R
1J
0I
0W
0N
1H
1Q
17
16
0a
1b
1W
0G
0P
08
1^
0i
0(
1P
0Z
1[
19
0:
18
0f
1{
0r
1i
0k
1f
0o
1x
0d
1k
0t
1}
1v
0m
1d
0)
1)
0*
1+
#300000
0$
0%
1&
0?
0>
0=
0B
0A
0@
1E
1D
1C
13
14
15
00
01
02
0-
0.
0/
0i
1j
1r
0{
1|
0M
0V
0_
0'
0\
0S
0J
1y
0x
1o
1g
0f
1a
0b
0}
1t
0k
1e
1w
0H
0Q
07
06
1;
0^
0a
0W
1,
0t
1u
0d
1m
0v
1Z
0[
09
1:
1q
1{
0|
0r
1s
0+
1*
0)
0m
0P
0Z
1n
1<
0:
08
1p
0o
0y
1x
1~
1r
0s
1i
0j
0*
1t
0u
0w
0q
0g
1f
0p
1o
1z
0,
1m
1k
0t
1u
1w
0n
0e
0;
0<
1q
1t
0u
1}
0~
1,
0m
1d
1*
1n
1<
0z
0q
0}
1~
1)
0*
1v
1m
0n
0w
0<
1z
0,
1}
0~
1*
1+
0v
1w
0z
1,
0+
1v
0w
0,
1+
#305000
1$
1?
1>
1=
1-
1.
1/
1L
1U
1'
1R
1I
1W
1N
1G
1P
18
0i
1j
1(
1g
0f
0k
1e
1;
0t
1u
0d
1q
0)
0m
1n
1<
0}
1~
0*
1z
0v
1w
1,
0+
#310000
0$
1%
0?
0>
0=
1B
1A
1@
10
11
12
0-
0.
0/
1_
0'
1\
1a
1Z
1:
0r
1s
1p
0o
1t
0u
0q
1m
1*
#315000
1$
1?
1>
1=
1-
1.
1/
0L
1M
0U
1V
1'
1S
0R
1J
0I
0W
0N
1H
1Q
17
16
0a
1b
1W
0G
0P
08
1^
1i
0j
0(
1P
0Z
1[
19
0:
18
0g
1f
0{
1|
1r
0s
0i
1j
1k
0e
0;
1g
0f
0p
1o
1y
0x
1d
0k
1}
0~
0n
1e
1;
0<
0z
0t
1u
0}
1v
0d
1)
1q
0)
1+
0v
0m
1n
1<
1}
0*
0+
1v
1+
