ex01/Programming_task_1/halfadder.sv
module halfadder (
  input logic a, b,
  output logic s, c
);

  assign s = a ^ b;
  assign c = a & b;

endmodule

ex01/Programming_task_1/fulladder.sv
`include "halfadder.sv"

module fulladder(
  input logic a, b, c_in,
  output logic s, c_out
);

wire sum1, carry1, carry2;

halfadder first ( a, b, sum1, carry1);
halfadder second(sum1, c_in, s, carry2);

or carryOr(c_out, carry1, carry2);

endmodule

ex01/Programming_task_3/and.sv
module and_gate(
  input logic a, b,
  output logic o
);

  assign o = a & b;

endmodule

ex01/Programming_task_3/mult.sv
`include "and.sv"
`include "fulladder.sv"

module mult(
  input  logic a0, a1, a2, b0, b1, b2,
  output logic s0, s1, s2, s3, s4, s5
);

// Partial products for 1st bit of B
// ppBA (bit B from B, bit A from A)
and_gate and1 (b0, a0, pp_00);
and_gate and2 (b0, a1, pp_01);
and_gate and3 (b0, a2, pp_02);

// Partial products for 2nd bit of B
and_gate and4 (b1, a0, pp_10);
and_gate and5 (b1, a1, pp_11);
and_gate and6 (b1, a2, pp_12);

// Partial products for 3rd bit of B
and_gate and7 (b2, a0, pp_20);
and_gate and8 (b2, a1, pp_21);
and_gate and9 (b2, a2, pp_22);

// buf(out, in) just propagates the same value
buf(s0, a0);

// Summations: Row 1
// Full-Adder names: fXY (X=row, Y=number of the adder from left)
fulladder f11 (
  .a(pp_01),
  .b(pp_10),
  .c_in(0),
  .s(s1),
  .c_out(carry_for_f12)
);

fulladder f12 (
  .a(pp_02),
  .b(pp_11),
  .c_in(carry_for_f12),
  .s(sum_for_f21),
  .c_out(carry_for_f13)
);

fulladder f13 (
  .a(pp_12),
  .b(0),
  .c_in(0),
  .s(sum_for_f22),
  .c_out(b_for_f23)
);

// Row 2
fulladder f21 (
  .a(pp_20),
  .b(sum_for_f21),
  .c_in(0),
  .s(s2),
  .c_out(carry_for_f22)
);

fulladder f22 (
  .a(pp_21),
  .b(sum_for_f22),
  .c_in(carry_for_f22),
  .s(s3),
  .c_out(carry_for_f23)
);

fulladder f23 (
  .a(pp_22),
  .b(b_for_f23),
  .c_in(carry_for_f23),
  .s(s4),
  .c_out(s5)
);

endmodule

ex01/vcd_files/mult.vcd
$date
    May  4, 2025  22:47:37
$end
$comment
	SimVision SST: d37fa0eb34ee6115b71f12b7fe0b461f
$end
$version
    TOOL:	xmsim(64)	22.09-s007
$end
$timescale
    1 fs
$end

$scope module mult $end
$var wire      1 !    a0  $end
$var wire      1 "    a1  $end
$var wire      1 #    a2  $end
$var wire      1 $    b0  $end
$var wire      1 %    b1  $end
$var wire      1 &    b2  $end
$var reg       1 '    s0 $end
$var reg       1 (    s1 $end
$var reg       1 )    s2 $end
$var reg       1 *    s3 $end
$var reg       1 +    s4 $end
$var reg       1 ,    s5 $end
$var wire      1 -    pp_00  $end
$var wire      1 .    pp_01  $end
$var wire      1 /    pp_02  $end
$var wire      1 0    pp_10  $end
$var wire      1 1    pp_11  $end
$var wire      1 2    pp_12  $end
$var wire      1 3    pp_20  $end
$var wire      1 4    pp_21  $end
$var wire      1 5    pp_22  $end
$var wire      1 6    carry_for_f12  $end
$var wire      1 7    carry_for_f13  $end
$var wire      1 8    sum_for_f21  $end
$var wire      1 9    b_for_f23  $end
$var wire      1 :    sum_for_f22  $end
$var wire      1 ;    carry_for_f22  $end
$var wire      1 <    carry_for_f23  $end

$scope module and1 $end
$var wire      1 $    a  $end
$var wire      1 !    b  $end
$var reg       1 =    o $end
$upscope $end


$scope module and2 $end
$var wire      1 $    a  $end
$var wire      1 "    b  $end
$var reg       1 >    o $end
$upscope $end


$scope module and3 $end
$var wire      1 $    a  $end
$var wire      1 #    b  $end
$var reg       1 ?    o $end
$upscope $end


$scope module and4 $end
$var wire      1 %    a  $end
$var wire      1 !    b  $end
$var reg       1 @    o $end
$upscope $end


$scope module and5 $end
$var wire      1 %    a  $end
$var wire      1 "    b  $end
$var reg       1 A    o $end
$upscope $end


$scope module and6 $end
$var wire      1 %    a  $end
$var wire      1 #    b  $end
$var reg       1 B    o $end
$upscope $end


$scope module and7 $end
$var wire      1 &    a  $end
$var wire      1 !    b  $end
$var reg       1 C    o $end
$upscope $end


$scope module and8 $end
$var wire      1 &    a  $end
$var wire      1 "    b  $end
$var reg       1 D    o $end
$upscope $end


$scope module and9 $end
$var wire      1 &    a  $end
$var wire      1 #    b  $end
$var reg       1 E    o $end
$upscope $end


$scope module f11 $end
$var wire      1 .    a  $end
$var wire      1 0    b  $end
$var wire      1 F    c_in  $end
$var reg       1 G    s $end
$var reg       1 H    c_out $end
$var wire      1 I    sum1  $end
$var wire      1 J    carry1  $end
$var wire      1 K    carry2  $end

$scope module first $end
$var wire      1 .    a  $end
$var wire      1 0    b  $end
$var reg       1 L    s $end
$var reg       1 M    c $end
$upscope $end


$scope module second $end
$var wire      1 I    a  $end
$var wire      1 F    b  $end
$var reg       1 N    s $end
$var reg       1 O    c $end
$upscope $end

$upscope $end


$scope module f12 $end
$var wire      1 /    a  $end
$var wire      1 1    b  $end
$var wire      1 6    c_in  $end
$var reg       1 P    s $end
$var reg       1 Q    c_out $end
$var wire      1 R    sum1  $end
$var wire      1 S    carry1  $end
$var wire      1 T    carry2  $end

$scope module first $end
$var wire      1 /    a  $end
$var wire      1 1    b  $end
$var reg       1 U    s $end
$var reg       1 V    c $end
$upscope $end


$scope module second $end
$var wire      1 R    a  $end
$var wire      1 6    b  $end
$var reg       1 W    s $end
$var reg       1 X    c $end
$upscope $end

$upscope $end


$scope module f13 $end
$var wire      1 2    a  $end
$var wire      1 Y    b  $end
$var wire      1 7    c_in  $end
$var reg       1 Z    s $end
$var reg       1 [    c_out $end
$var wire      1 \    sum1  $end
$var wire      1 ]    carry1  $end
$var wire      1 ^    carry2  $end

$scope module first $end
$var wire      1 2    a  $end
$var wire      1 Y    b  $end
$var reg       1 _    s $end
$var reg       1 `    c $end
$upscope $end


$scope module second $end
$var wire      1 \    a  $end
$var wire      1 7    b  $end
$var reg       1 a    s $end
$var reg       1 b    c $end
$upscope $end

$upscope $end


$scope module f21 $end
$var wire      1 3    a  $end
$var wire      1 8    b  $end
$var wire      1 c    c_in  $end
$var reg       1 d    s $end
$var reg       1 e    c_out $end
$var wire      1 f    sum1  $end
$var wire      1 g    carry1  $end
$var wire      1 h    carry2  $end

$scope module first $end
$var wire      1 3    a  $end
$var wire      1 8    b  $end
$var reg       1 i    s $end
$var reg       1 j    c $end
$upscope $end


$scope module second $end
$var wire      1 f    a  $end
$var wire      1 c    b  $end
$var reg       1 k    s $end
$var reg       1 l    c $end
$upscope $end

$upscope $end


$scope module f22 $end
$var wire      1 4    a  $end
$var wire      1 :    b  $end
$var wire      1 ;    c_in  $end
$var reg       1 m    s $end
$var reg       1 n    c_out $end
$var wire      1 o    sum1  $end
$var wire      1 p    carry1  $end
$var wire      1 q    carry2  $end

$scope module first $end
$var wire      1 4    a  $end
$var wire      1 :    b  $end
$var reg       1 r    s $end
$var reg       1 s    c $end
$upscope $end


$scope module second $end
$var wire      1 o    a  $end
$var wire      1 ;    b  $end
$var reg       1 t    s $end
$var reg       1 u    c $end
$upscope $end

$upscope $end


$scope module f23 $end
$var wire      1 5    a  $end
$var wire      1 9    b  $end
$var wire      1 <    c_in  $end
$var reg       1 v    s $end
$var reg       1 w    c_out $end
$var wire      1 x    sum1  $end
$var wire      1 y    carry1  $end
$var wire      1 z    carry2  $end

$scope module first $end
$var wire      1 5    a  $end
$var wire      1 9    b  $end
$var reg       1 {    s $end
$var reg       1 |    c $end
$upscope $end


$scope module second $end
$var wire      1 x    a  $end
$var wire      1 <    b  $end
$var reg       1 }    s $end
$var reg       1 ~    c $end
$upscope $end

$upscope $end

$upscope $end

$enddefinitions $end
$dumpvars
0!
0"
0#
0$
0%
0&
0'
0(
0)
0*
0+
0,
0-
0.
0/
00
01
02
03
04
05
06
07
08
09
0:
0;
0<
0=
0>
0?
0@
0A
0B
0C
0D
0E
0F
0G
0H
0I
0J
0K
0L
0M
0N
0O
0P
0Q
0R
0S
0T
0U
0V
0W
0X
0Y
0Z
0[
0\
0]
0^
0_
0`
0a
0b
0c
0d
0e
0f
0g
0h
0i
0j
0k
0l
0m
0n
0o
0p
0q
0r
0s
0t
0u
0v
0w
0x
0y
0z
0{
0|
0}
0~
$end
#5000
1!
1"
1#
#10000
0!
0"
0#
#15000
1$
1%
1&
#20000
1!
1"
1#
1C
1@
1=
1D
1A
1>
1E
1B
1?
1/
12
15
1.
11
14
1-
10
13
1V
1_
1{
1M
1r
1i
1'
1f
1o
1J
1x
1\
1S
1k
1t
1}
1a
1Q
1H
16
17
1W
0a
1b
1Z
1v
1m
1d
1:
1^
1)
1*
1+
0r
1s
0Z
1P
1[
19
18
0:
1p
0o
0{
1|
0i
1j
1r
0s
0t
1n
1<
0p
1o
1g
0f
1y
0x
0m
1t
0k
1w
1e
0n
0<
1;
0}
0t
1u
1,
0d
1m
0*
1q
1*
0)
0m
0v
1n
1<
1}
0+
0*
1v
1+
#25000
0&
0#
0E
0D
0C
0B
0?
0/
02
03
04
05
1U
0V
0_
1i
0j
0r
1{
0|
0y
1x
0o
0g
1f
0\
0S
1R
0}
1~
1t
0u
1k
1a
0b
0W
1X
0Q
0e
0w
0;
07
1T
0^
0q
1z
0,
0t
0a
0P
1Z
1d
1m
0v
1w
0n
0[
1Q
17
09
0<
1:
08
1a
0{
1}
0~
1,
0+
1*
1)
1r
0i
0Z
0m
0:
0f
1o
0z
0x
0*
0r
0k
1t
1v
0}
1Z
0w
1:
0o
0,
1r
0v
1+
1m
0d
0t
1o
0m
0)
1*
0+
1t
1m
0*
1*
#30000
0!
0@
0=
0-
00
1L
0M
0'
0J
1I
1N
0H
06
1W
0X
1G
0T
1(
1P
0Q
07
18
0a
1i
1f
1k
0Z
0:
0r
1d
0o
1)
0t
0m
0*
#35000
1&
1D
14
1r
1o
1t
1m
1*
#40000
0"
1!
0D
0A
0>
1C
1@
1=
1-
10
13
0.
01
04
0i
1j
0U
0r
1'
0o
0R
1g
0f
0t
0W
0k
1e
1;
1t
0d
0P
0m
08
0*
1i
0j
0)
1m
0g
1f
1*
1k
0e
0;
0t
1d
1)
0m
0*
#45000
0%
0@
00
0L
0I
0N
0G
0(
#50000
0$
1%
0&
0=
1@
0C
03
10
0-
0i
1L
0'
1I
0f
1N
0k
0d
1G
1(
0)
