ex06/Programming_Task_2/hls/vitis_hls/solution1/impl/verilog/crypt_message.v
// ==============================================================
// RTL generated by Vitis HLS - High-Level Synthesis from C, C++ and OpenCL v2022.2 (64-bit)
// Version: 2022.2
// Copyright (C) Copyright 1986-2022 Xilinx, Inc. All Rights Reserved.
// 
// ===========================================================

`timescale 1 ns / 1 ps 

(* CORE_GENERATION_INFO="crypt_message_crypt_message,hls_ip_2022_2,{HLS_INPUT_TYPE=cxx,HLS_INPUT_FLOAT=0,HLS_INPUT_FIXED=0,HLS_INPUT_PART=xc7vx485t-ffg1761-2,HLS_INPUT_CLOCK=50.000000,HLS_INPUT_ARCH=others,HLS_SYN_CLOCK=2.168000,HLS_SYN_LAT=0,HLS_SYN_TPT=none,HLS_SYN_MEM=0,HLS_SYN_DSP=0,HLS_SYN_FF=0,HLS_SYN_LUT=112,HLS_VERSION=2022_2}" *)

module crypt_message (
        ap_start,
        ap_done,
        ap_idle,
        ap_ready,
        encrypt_decrypt,
        message,
        key,
        ap_return
);


input   ap_start;
output   ap_done;
output   ap_idle;
output   ap_ready;
input   encrypt_decrypt;
input  [63:0] message;
input  [15:0] key;
output  [63:0] ap_return;

wire   [15:0] chunk_V_fu_64_p1;
wire   [0:0] next_key_V_fu_74_p0;
wire   [15:0] ret_fu_68_p2;
wire   [15:0] next_key_V_fu_74_p3;
wire   [15:0] chunk_V_1_fu_82_p4;
wire   [0:0] next_key_V_1_fu_98_p0;
wire   [15:0] ret_1_fu_92_p2;
wire   [15:0] next_key_V_1_fu_98_p3;
wire   [15:0] chunk_V_2_fu_106_p4;
wire   [0:0] next_key_V_2_fu_122_p0;
wire   [15:0] ret_2_fu_116_p2;
wire   [15:0] next_key_V_2_fu_122_p3;
wire   [15:0] chunk_V_3_fu_130_p4;
wire   [15:0] ret_3_fu_140_p2;
wire    ap_ce_reg;

assign ap_done = ap_start;

assign ap_idle = 1'b1;

assign ap_ready = ap_start;

assign ap_return = {{{{ret_3_fu_140_p2}, {ret_2_fu_116_p2}}, {ret_1_fu_92_p2}}, {ret_fu_68_p2}};

assign chunk_V_1_fu_82_p4 = {{message[31:16]}};

assign chunk_V_2_fu_106_p4 = {{message[47:32]}};

assign chunk_V_3_fu_130_p4 = {{message[63:48]}};

assign chunk_V_fu_64_p1 = message[15:0];

assign next_key_V_1_fu_98_p3 = ((next_key_V_1_fu_98_p0[0:0] == 1'b1) ? chunk_V_1_fu_82_p4 : ret_1_fu_92_p2);

assign next_key_V_2_fu_122_p3 = ((next_key_V_2_fu_122_p0[0:0] == 1'b1) ? chunk_V_2_fu_106_p4 : ret_2_fu_116_p2);

assign next_key_V_fu_74_p3 = ((next_key_V_fu_74_p0[0:0] == 1'b1) ? chunk_V_fu_64_p1 : ret_fu_68_p2);

assign ret_1_fu_92_p2 = (next_key_V_fu_74_p3 ^ chunk_V_1_fu_82_p4);

assign ret_2_fu_116_p2 = (next_key_V_1_fu_98_p3 ^ chunk_V_2_fu_106_p4);

assign ret_3_fu_140_p2 = (next_key_V_2_fu_122_p3 ^ chunk_V_3_fu_130_p4);

assign ret_fu_68_p2 = (key ^ chunk_V_fu_64_p1);

assign next_key_V_1_fu_98_p0 = encrypt_decrypt;

assign next_key_V_2_fu_122_p0 = encrypt_decrypt;

assign next_key_V_fu_74_p0 = encrypt_decrypt;

endmodule //crypt_message

ex02/Programming_Task_0/xor_chunk.sv
module xor_chunk # (
  parameter n = 1
) (
  input logic  [n*8-1:0] chunk,
  input logic  [n*8-1:0] key,
  output logic [n*8-1:0] out
);

  assign out = chunk ^ key;

endmodule

ex02/Programming_Task_2/cbc.sv
module cbc # (
  parameter n = 1,
  parameter m = 3
) (
  input logic enc_dec,
  input logic  [n*m*8-1:0] message,
  input logic  [n*8-1:0] key,
  output logic [n*m*8-1:0] out
);

// First message chunk uses key and only generate if message is not of 0 length
if (m != 0) begin
  xor_chunk # (
    .n(n)
  ) chunk_first (
    .chunk(message[n*8-1:0]),
    .key(key),
    .out(out[n*8-1:0])
  );
end


// Generate remaining chunks
for (genvar chunk = 1; chunk < m; chunk++) begin: gen_chunk_xors

  logic [n*8-1:0] current_key;

  // Decide whether to select output (encryption, enc_dec=0) or chunk (decryption, enc_dec=1) as next key using multiplexers
  always_comb begin
    current_key = enc_dec ? message[(chunk)*n*8-1:(chunk-1)*n*8] : out[(chunk)*n*8-1:(chunk-1)*n*8];
  end

  xor_chunk # (
    .n(n)
  ) chunk_after (
    .chunk(message[(chunk+1)*n*8-1:chunk*n*8]),
    .key(current_key),  // Output of previous chunk is key for the next chunk
    .out(out[(chunk+1)*n*8-1:chunk*n*8])
  );

end


endmodule

ex06/Programming_Task_2/cbc_testbench.sv
module cbc_testbench;

// m = 4, n = 2
logic encrypt_decrypt;
logic [15:0] key;
logic [63:0] message;
logic [63:0] result;
logic [63:0] result_exercise2;

logic clock = 'b0;
logic reset = 'b0;
logic start = 'b0;

// Other outputs
logic done;
logic idle;
logic ready;

// CBC from exercise 2
cbc # (
  .n(2),
  .m(4)
) crypter_exercise2 (
  .enc_dec(encrypt_decrypt),
  .message(message),
  .key(key),
  .out(result_exercise2)
);


// HLS unroll CBC
crypt_message cbc (
        .ap_start(start),
        .ap_done(done),
        .ap_idle(idle),
        .ap_ready(ready),
        .encrypt_decrypt(encrypt_decrypt),
        .message(message),
        .key(key),
        .ap_return(result)
);


// We still keep a clock for property checking even though not needed
always #(55ns) clock = ~clock;

// Check whether on all positive clock edges the outputs are the same
property mirror_check;
  disable iff (reset)
  @(posedge clock) result === result_exercise2;
endproperty

assert property (mirror_check);	


// Here we first have a few manual test cases
// and afterwards simulate 50 random encryptions and 50 decryptions
// We rely on the property to check whether the our outputs are the same as the CBC from exercise02,
// which works correctly
initial begin
  reset = 'b0;
  encrypt_decrypt = 'b0;
  start = 'b0;
  #(56ns)


  // 2 simple encryption tests
  start = 'b1;
  message = 'h0;
  key     = 'b11100111; // 00E7
  // Result will be 00E7_00E7_00E7_00E7, key just gets copied
  #(550ns);
  encrypt1: assert (result == 'h00E7_00E7_00E7_00E7);

  start = 'b1;
  message = 'h1111_1234_1100_11E7;
  key     = 'b11100111; // 00E7
  // Result of first chunk (lsbs) will be (11E7 ^ 00E7) = 1100
  // with 2nd: 1100 ^ 1100 = 0000
  // with 3rd: 0000 ^ 1234 = 1234
  // with 4th: 1111 ^ 1234 = 0325
  // 1100_1100_1100_1100
  #(550ns);
  encrypt2: assert (result == 'h0325_1234_0000_1100);

  // 2 simple decryption tests
  encrypt_decrypt = 'b1;
  message = 'h0325_1234_0000_1100;
  key     = 'b11100111; // 00E7
  #(550ns);
  decrypt1: assert (result == 'h1111_1234_1100_11E7);

  encrypt_decrypt = 'b1;
  message = 'h00E7_00E7_00E7_00E7;
  key     = 'b11100111; // 00E7
  #(550ns);
  decrypt2: assert (result == 'h0);

  // Randomness!
  // Encryption
  encrypt_decrypt = 'b0;
  for (int i=0; i<50; i++) begin
    message = $random;
    key = $random;
    #(550ns);
  end

  // Decryption
  encrypt_decrypt = 'b1;
  #(55ns)
  for (int i=0; i<50; i++) begin
    message = $random;
    key = $random;
    #(550ns);
  end

  $finish;

end





endmodule

ex06/vcd_files/cbc_hls_unrolled.vcd
$date
    Jun 28, 2025  17:45:10
$end
$comment
	SimVision SST: d37fa0eb34ee6115b71f12b7fe0b461f
$end
$version
    TOOL:	xmsim(64)	22.09-s007
$end
$timescale
    1 ps
$end

$scope module cbc_testbench $end
$var reg       1 !    encrypt_decrypt $end
$var reg      16 "    key [15:0] $end
$var reg      64 #    message [63:0] $end
$var reg      64 $    result [63:0] $end
$var reg      64 %    result_exercise2 [63:0] $end
$var reg       1 &    clock $end
$var reg       1 '    reset $end
$var reg       1 (    start $end
$var reg       1 )    done $end
$var reg       1 *    idle $end
$var reg       1 +    ready $end

$scope module crypter_exercise2 $end
$var parameter 32 ,    n $end
$var parameter 32 -    m $end
$var wire      1 .    enc_dec  $end
$var wire     64 /    message [63:0] $end
$var wire     16 0    key [15:0] $end
$var reg      64 1    out [63:0] $end

$scope begin genblk1 $end

$scope module chunk_first $end
$var parameter 32 2    n $end
$var wire     16 3    chunk [15:0] $end
$var wire     16 0    key [15:0] $end
$var reg      16 4    out [15:0] $end
$upscope $end

$upscope $end


$scope begin gen_chunk_xors[1] $end
$var parameter 32 5    chunk $end
$var reg      16 6    current_key [15:0] $end

$scope module chunk_after $end
$var parameter 32 7    n $end
$var wire     16 8    chunk [15:0] $end
$var wire     16 9    key [15:0] $end
$var reg      16 :    out [15:0] $end
$upscope $end

$upscope $end


$scope begin gen_chunk_xors[2] $end
$var parameter 32 ;    chunk $end
$var reg      16 <    current_key [15:0] $end

$scope module chunk_after $end
$var parameter 32 =    n $end
$var wire     16 >    chunk [15:0] $end
$var wire     16 ?    key [15:0] $end
$var reg      16 @    out [15:0] $end
$upscope $end

$upscope $end


$scope begin gen_chunk_xors[3] $end
$var parameter 32 A    chunk $end
$var reg      16 B    current_key [15:0] $end

$scope module chunk_after $end
$var parameter 32 C    n $end
$var wire     16 D    chunk [15:0] $end
$var wire     16 E    key [15:0] $end
$var reg      16 F    out [15:0] $end
$upscope $end

$upscope $end

$upscope $end


$scope module cbc $end
$var wire      1 G    ap_start  $end
$var wire      1 H    ap_done  $end
$var wire      1 I    ap_idle  $end
$var wire      1 J    ap_ready  $end
$var wire      1 K    encrypt_decrypt  $end
$var wire     64 L    message [63:0] $end
$var wire     16 M    key [15:0] $end
$var wire     64 N    ap_return [63:0] $end
$var wire     16 O    chunk_V_fu_64_p1 [15:0] $end
$var wire      1 P    next_key_V_fu_74_p0 [0] $end
$var wire     16 Q    ret_fu_68_p2 [15:0] $end
$var wire     16 R    next_key_V_fu_74_p3 [15:0] $end
$var wire     16 S    chunk_V_1_fu_82_p4 [15:0] $end
$var wire      1 T    next_key_V_1_fu_98_p0 [0] $end
$var wire     16 U    ret_1_fu_92_p2 [15:0] $end
$var wire     16 V    next_key_V_1_fu_98_p3 [15:0] $end
$var wire     16 W    chunk_V_2_fu_106_p4 [15:0] $end
$var wire      1 X    next_key_V_2_fu_122_p0 [0] $end
$var wire     16 Y    ret_2_fu_116_p2 [15:0] $end
$var wire     16 Z    next_key_V_2_fu_122_p3 [15:0] $end
$var wire     16 [    chunk_V_3_fu_130_p4 [15:0] $end
$var wire     16 \    ret_3_fu_140_p2 [15:0] $end
$var wire      1 ]    ap_ce_reg  $end
$upscope $end

$upscope $end

$enddefinitions $end
$dumpvars
b10 C
b11 A
b10 =
b10 ;
b10 7
b1 5
b10 2
b100 -
b10 ,
0!
bx "
bx #
bx $
bx %
0&
0'
0(
0)
1*
0+
0.
bx /
bx 0
bx 1
bx 3
bx 4
bx 6
bx 8
bx 9
bx :
bx <
bx >
bx ?
bx @
bx B
bx D
bx E
bx F
0G
0H
1I
0J
0K
bx L
bx M
bx N
bx O
0P
bx Q
bx R
bx S
0T
bx U
bx V
bx W
0X
bx Y
bx Z
bx [
bx \
z]
$end
#55000
1&
#56000
1(
b0 #
b11100111 "
b11100111 M
b11100111 0
b0 L
b0 /
1G
1J
1H
1+
1)
b0 3
b0 D
b0 >
b0 8
b0 O
b0 [
b0 W
b0 S
b11100111 4
b11100111 Q
bx0000000011100111 1
b11100111 6
b11100111 9
bx0000000011100111 N
b11100111 R
b11100111 :
bx0000000011100111 %
bx0000000011100111 $
b11100111 U
bx00000000111001110000000011100111 1
b11100111 <
b11100111 ?
bx00000000111001110000000011100111 N
b11100111 V
b11100111 @
bx00000000111001110000000011100111 %
bx00000000111001110000000011100111 $
b11100111 Y
bx000000001110011100000000111001110000000011100111 1
b11100111 B
b11100111 E
bx000000001110011100000000111001110000000011100111 N
b11100111 Z
b11100111 F
bx000000001110011100000000111001110000000011100111 %
bx000000001110011100000000111001110000000011100111 $
b11100111 \
b11100111000000001110011100000000111001110000000011100111 1
b11100111000000001110011100000000111001110000000011100111 N
b11100111000000001110011100000000111001110000000011100111 %
b11100111000000001110011100000000111001110000000011100111 $
#110000
0&
#165000
1&
#220000
0&
#275000
1&
#330000
0&
#385000
1&
#440000
0&
#495000
1&
#550000
0&
#605000
1&
#606000
b1000100010001000100100011010000010001000000000001000111100111 #
b1000100010001000100100011010000010001000000000001000111100111 L
b1000100010001000100100011010000010001000000000001000111100111 /
b1000111100111 3
b1000100010001 D
b1001000110100 >
b1000100000000 8
b1000111100111 O
b1000100010001 [
b1001000110100 W
b1000100000000 S
b1000100000000 4
b1000111110110 F
b1001011010011 @
b1000111100111 :
b1000111100111 U
b1001011010011 Y
b1000111110110 \
b1000100000000 Q
b11100111000000001110011100010001111001110000000011100111 1
b11100111000100101101001100010001111001110000000011100111 1
b1000111110110000100101101001100010001111001110000000011100111 1
b1000111110110000100101101001100010001111001110001000100000000 1
b1000100000000 6
b1000111100111 <
b1001011010011 B
b1001011010011 E
b1000111100111 ?
b1000100000000 9
b1000100000000 R
b1001011010011 Z
b1000111110110000100101101001100010001111001110001000100000000 N
b1000111100111 V
b1111000010 F
b1111010011 @
b0 :
b1000111110110000100101101001100010001111001110001000100000000 %
b1000111110110000100101101001100010001111001110001000100000000 $
b1111010011 Y
b1111000010 \
b0 U
b1000111110110000100101101001100000000000000000001000100000000 1
b1000111110110000000111101001100000000000000000001000100000000 1
b1111000010000000111101001100000000000000000001000100000000 1
b0 <
b1111010011 B
b1111010011 E
b0 ?
b0 V
b1111000010000000111101001100000000000000000001000100000000 N
b1111010011 Z
b1001011000010 F
b1001000110100 @
b1111000010000000111101001100000000000000000001000100000000 %
b1111000010000000111101001100000000000000000001000100000000 $
b1001011000010 \
b1001000110100 Y
b1111000010000100100011010000000000000000000001000100000000 1
b1001011000010000100100011010000000000000000000001000100000000 1
b1001000110100 B
b1001000110100 E
b1001000110100 Z
b1001011000010000100100011010000000000000000000001000100000000 N
b1100100101 F
b1001011000010000100100011010000000000000000000001000100000000 %
b1001011000010000100100011010000000000000000000001000100000000 $
b1100100101 \
b1100100101000100100011010000000000000000000001000100000000 1
b1100100101000100100011010000000000000000000001000100000000 N
b1100100101000100100011010000000000000000000001000100000000 %
b1100100101000100100011010000000000000000000001000100000000 $
#660000
0&
#715000
1&
#770000
0&
#825000
1&
#880000
0&
#935000
1&
#990000
0&
#1045000
1&
#1100000
0&
#1155000
1&
#1156000
1!
b1100100101000100100011010000000000000000000001000100000000 #
b1100100101000100100011010000000000000000000001000100000000 L
b1100100101000100100011010000000000000000000001000100000000 /
1K
1.
1P
1X
1T
b1000100000000 V
b1000111100111 R
b1000100000000 3
b1100100101 D
b0 8
b1000100000000 O
b1100100101 [
b0 S
b1000111100111 4
b1000100010001 F
b1000100000000 :
b0 V
b1000100010001 \
b1000100000000 R
b1000111100111 Q
b1000111100111 U
b1100110100 Y
b1100100101000100100011010000010001000000000001000100000000 1
b1000100010001000100100011010000010001000000000001000100000000 1
b1000100010001000100100011010000010001000000000001000111100111 1
b1000100000000 U
b1000100010001000000110011010000010001111001110001000111100111 N
b1001000110100 Y
b1000100010001000100100011010000010001000000000001000111100111 %
b1000100010001000000110011010000010001111001110001000111100111 $
b1000100010001000100100011010000010001000000000001000111100111 N
b1000100010001000100100011010000010001000000000001000111100111 $
#1210000
0&
#1265000
1&
#1320000
0&
#1375000
1&
#1430000
0&
#1485000
1&
#1540000
0&
#1595000
1&
#1650000
0&
#1705000
1&
#1706000
b11100111000000001110011100000000111001110000000011100111 #
b11100111000000001110011100000000111001110000000011100111 L
b11100111000000001110011100000000111001110000000011100111 /
b11100111 B
b11100111 <
b11100111 6
b11100111 9
b11100111 ?
b11100111 E
b11100111 3
b11100111 D
b11100111 >
b11100111 8
b11100111 O
b11100111 [
b11100111 W
b11100111 S
b0 :
b0 @
b0 F
b0 4
b11100111 V
b1000111100111 U
b11100111 Z
b11100111 Y
b1001011010011 \
b11100111 R
b0 Q
b1000100010001000100100011010000010001000000000000000000000000 1
b100100011010000010001000000000000000000000000 1
b10001000000000000000000000000 1
b0 1
b0 U
b0 \
b1001011010011000000001110011100010001111001110000000000000000 N
b0 Y
b0 %
b1001011010011000000001110011100010001111001110000000000000000 $
b0 N
b0 $
#1760000
0&
#1815000
1&
#1870000
0&
#1925000
1&
#1980000
0&
#2035000
1&
#2090000
0&
#2145000
1&
#2200000
0&
#2255000
1&
#2256000
0!
b10010000101010011010100100100 #
b101111010000001 "
b101111010000001 M
b101111010000001 0
b10010000101010011010100100100 L
b10010000101010011010100100100 /
0K
0.
0P
0X
0T
b101111001100110 4
b0 B
b0 <
b0 6
b0 9
b0 ?
b0 E
b0 V
b0 Z
b0 R
b11010100100100 3
b0 D
b0 >
b1001000010101 8
b11010100100100 O
b0 [
b0 W
b1001000010101 S
b101111001100110 Q
b1001000010101 :
b110101110100101 4
b101111001100110 1
b101111001100110 6
b101111001100110 9
b101111001100110 N
b101111001100110 R
b110101110100101 Q
b1001000010101 U
b100110001110011 :
b101111001100110 $
b101111001100110 %
b110101110100101 1
b10010000101010110101110100101 1
b110101110100101 6
b1001000010101 <
b1001000010101 ?
b110101110100101 9
b1001000010101 V
b10010000101010110101110100101 N
b110101110100101 R
b100110001110011 U
b1001000010101 @
b111100110110000 :
b10010000101010110101110100101 %
b10010000101010110101110100101 $
b1001100011100110110101110100101 1
b100110001110011 <
b100110001110011 ?
b1001100011100110110101110100101 N
b100110001110011 V
b111100110110000 U
b1001000010101 Y
b100110001110011 @
b1001100011100110110101110100101 %
b1001100011100110110101110100101 $
b1111001101100000110101110100101 1
b100100001010101111001101100000110101110100101 1
b111100110110000 <
b1001000010101 B
b1001000010101 E
b111100110110000 ?
b1001000010101 Z
b100100001010101111001101100000110101110100101 N
b111100110110000 V
b100110001110011 Y
b1001000010101 F
b111100110110000 @
b100100001010101111001101100000110101110100101 %
b100100001010101111001101100000110101110100101 $
b10011000111001101111001101100000110101110100101 1
b100110001110011 B
b100110001110011 E
b10011000111001101111001101100000110101110100101 N
b100110001110011 Z
b111100110110000 Y
b1001000010101 \
b100110001110011 F
b10011000111001101111001101100000110101110100101 %
b10011000111001101111001101100000110101110100101 $
b11110011011000001111001101100000110101110100101 1
b1001000010101011110011011000001111001101100000110101110100101 1
b111100110110000 B
b111100110110000 E
b1001000010101011110011011000001111001101100000110101110100101 N
b111100110110000 Z
b100110001110011 \
b111100110110000 F
b1001000010101011110011011000001111001101100000110101110100101 %
b1001000010101011110011011000001111001101100000110101110100101 $
b100110001110011011110011011000001111001101100000110101110100101 1
b100110001110011011110011011000001111001101100000110101110100101 N
b111100110110000 \
b100110001110011011110011011000001111001101100000110101110100101 %
b100110001110011011110011011000001111001101100000110101110100101 $
b111100110110000011110011011000001111001101100000110101110100101 1
b111100110110000011110011011000001111001101100000110101110100101 N
b111100110110000011110011011000001111001101100000110101110100101 %
b111100110110000011110011011000001111001101100000110101110100101 $
#2310000
0&
#2365000
1&
#2420000
0&
#2475000
1&
#2530000
0&
#2585000
1&
#2640000
0&
#2695000
1&
#2750000
0&
#2805000
1&
#2806000
b1111111111111111111111111111111110000100100001001101011000001001 #
b101011001100011 "
b101011001100011 M
b101011001100011 0
b1111111111111111111111111111111110000100100001001101011000001001 L
b1111111111111111111111111111111110000100100001001101011000001001 /
b110001101000111 4
b1101011000001001 3
b1111111111111111 D
b1111111111111111 >
b1000010010000100 8
b1101011000001001 O
b1111111111111111 [
b1111111111111111 W
b1000010010000100 S
b110001101000111 Q
b1000000001101010 4
b1000011001001111 F
b1000011001001111 @
b1110111100100001 :
b111100110110000011110011011000001111001101100000110001101000111 1
b110001101000111 6
b110001101000111 9
b111100110110000011110011011000001111001101100000110001101000111 N
b1110111100100001 U
b1000011001001111 Y
b1000011001001111 \
b110001101000111 R
b1000000001101010 Q
b1110011111000011 :
b111100110110000011110011011000001111001101100000110001101000111 $
b111100110110000011110011011000001111001101100000110001101000111 %
b111100110110000011110011011000011101111001000010110001101000111 1
b111100110110000100001100100111111101111001000010110001101000111 1
b1000011001001111100001100100111111101111001000010110001101000111 1
b1000011001001111100001100100111111101111001000011000000001101010 1
b1000000001101010 6
b1110111100100001 <
b1000011001001111 B
b1000011001001111 E
b1110111100100001 ?
b1000000001101010 9
b1000000001101010 R
b1110011111000011 U
b1000011001001111 Z
b1000011001001111100001100100111111101111001000011000000001101010 N
b1110111100100001 V
b111100110110000 F
b1000011011110 @
b10011101110 :
b1000011001001111100001100100111111101111001000011000000001101010 %
b1000011001001111100001100100111111101111001000011000000001101010 $
b1000011001001111100001100100111111100111110000111000000001101010 1
b1110011111000011 <
b1110011111000011 ?
b1000011011110 Y
b111100110110000 \
b1000011001001111100001100100111111100111110000111000000001101010 N
b1110011111000011 V
b10011101110 U
b1100000111100 @
b1000011001001111100001100100111111100111110000111000000001101010 %
b1000011001001111100001100100111111100111110000111000000001101010 $
b1000011001001111100001100100111100000100111011101000000001101010 1
b1000011001001111000100001101111000000100111011101000000001101010 1
b111100110110000000100001101111000000100111011101000000001101010 1
b10011101110 <
b1000011011110 B
b1000011011110 E
b10011101110 ?
b10011101110 V
b1100000111100 Y
b111100110110000000100001101111000000100111011101000000001101010 N
b1000011011110 Z
b1110111100100001 F
b1111101100010001 @
b111100110110000000100001101111000000100111011101000000001101010 %
b111100110110000000100001101111000000100111011101000000001101010 $
b111100110110000000110000011110000000100111011101000000001101010 1
b1100000111100 B
b1100000111100 E
b1110111100100001 \
b111100110110000000110000011110000000100111011101000000001101010 N
b1100000111100 Z
b1111101100010001 Y
b1110011111000011 F
b111100110110000000110000011110000000100111011101000000001101010 %
b111100110110000000110000011110000000100111011101000000001101010 $
b111100110110000111110110001000100000100111011101000000001101010 1
b1110111100100001111110110001000100000100111011101000000001101010 1
b1111101100010001 B
b1111101100010001 E
b1111101100010001 Z
b1110011111000011 \
b1110111100100001111110110001000100000100111011101000000001101010 N
b10011101110 F
b1110111100100001111110110001000100000100111011101000000001101010 %
b1110111100100001111110110001000100000100111011101000000001101010 $
b1110011111000011111110110001000100000100111011101000000001101010 1
b1110011111000011111110110001000100000100111011101000000001101010 N
b10011101110 \
b1110011111000011111110110001000100000100111011101000000001101010 %
b1110011111000011111110110001000100000100111011101000000001101010 $
b10011101110111110110001000100000100111011101000000001101010 1
b10011101110111110110001000100000100111011101000000001101010 N
b10011101110111110110001000100000100111011101000000001101010 %
b10011101110111110110001000100000100111011101000000001101010 $
#2860000
0&
#2915000
1&
#2970000
0&
#3025000
1&
#3080000
0&
#3135000
1&
#3190000
0&
#3245000
1&
#3300000
0&
#3355000
1&
#3356000
b110101110010111101100001101 #
b1001100110001101 "
b1001100110001101 M
b1001100110001101 0
b110101110010111101100001101 L
b110101110010111101100001101 /
b100111110000100 4
b111101100001101 3
b0 D
b0 >
b11010111001 8
b111101100001101 O
b0 [
b0 W
b11010111001 S
b100111110000100 Q
b1110001010000000 4
b1111101100010001 F
b10011101110 @
b1000011011010011 :
b10011101110111110110001000100000100111011100100111110000100 1
b100111110000100 6
b100111110000100 9
b10011101110111110110001000100000100111011100100111110000100 N
b1000011011010011 U
b10011101110 Y
b1111101100010001 \
b100111110000100 R
b1110001010000000 Q
b100100100111101 :
b10011101110111110110001000100000100111011100100111110000100 $
b10011101110111110110001000100000100111011100100111110000100 %
b10011101110111110110001000110000110110100110100111110000100 1
b10011101110000001001110111010000110110100110100111110000100 1
b1111101100010001000001001110111010000110110100110100111110000100 1
b1111101100010001000001001110111010000110110100111110001010000000 1
b1110001010000000 6
b1000011011010011 <
b10011101110 B
b10011101110 E
b1000011011010011 ?
b1110001010000000 9
b1110001010000000 R
b100100100111101 U
b10011101110 Z
b1111101100010001000001001110111010000110110100111110001010000000 N
b1000011011010011 V
b10011101110 F
b1000011011010011 @
b1110010000111001 :
b1111101100010001000001001110111010000110110100111110001010000000 %
b1111101100010001000001001110111010000110110100111110001010000000 $
b1111101100010001000001001110111001001001001111011110001010000000 1
b100100100111101 <
b100100100111101 ?
b1000011011010011 Y
b10011101110 \
b1111101100010001000001001110111001001001001111011110001010000000 N
b100100100111101 V
b1110010000111001 U
b100100100111101 @
b1111101100010001000001001110111001001001001111011110001010000000 %
b1111101100010001000001001110111001001001001111011110001010000000 $
b1111101100010001000001001110111011100100001110011110001010000000 1
b1111101100010001100001101101001111100100001110011110001010000000 1
b10011101110100001101101001111100100001110011110001010000000 1
b1110010000111001 <
b1000011011010011 B
b1000011011010011 E
b1110010000111001 ?
b1110010000111001 V
b100100100111101 Y
b10011101110100001101101001111100100001110011110001010000000 N
b1000011011010011 Z
b1000011011010011 F
b1110010000111001 @
b10011101110100001101101001111100100001110011110001010000000 %
b10011101110100001101101001111100100001110011110001010000000 $
b10011101110010010010011110111100100001110011110001010000000 1
b100100100111101 B
b100100100111101 E
b1000011011010011 \
b10011101110010010010011110111100100001110011110001010000000 N
b100100100111101 Z
b1110010000111001 Y
b100100100111101 F
b10011101110010010010011110111100100001110011110001010000000 %
b10011101110010010010011110111100100001110011110001010000000 $
b10011101110111001000011100111100100001110011110001010000000 1
b1000011011010011111001000011100111100100001110011110001010000000 1
b1110010000111001 B
b1110010000111001 E
b1110010000111001 Z
b100100100111101 \
b1000011011010011111001000011100111100100001110011110001010000000 N
b1110010000111001 F
b1000011011010011111001000011100111100100001110011110001010000000 %
b1000011011010011111001000011100111100100001110011110001010000000 $
b100100100111101111001000011100111100100001110011110001010000000 1
b100100100111101111001000011100111100100001110011110001010000000 N
b1110010000111001 \
b100100100111101111001000011100111100100001110011110001010000000 %
b100100100111101111001000011100111100100001110011110001010000000 $
b1110010000111001111001000011100111100100001110011110001010000000 1
b1110010000111001111001000011100111100100001110011110001010000000 N
b1110010000111001111001000011100111100100001110011110001010000000 %
b1110010000111001111001000011100111100100001110011110001010000000 $
#3410000
0&
#3465000
1&
#3520000
0&
#3575000
1&
#3630000
0&
#3685000
1&
#3740000
0&
#3795000
1&
#3850000
0&
#3905000
1&
#3906000
b1111111111111111111111111111111110110010110000101000010001100101 #
b101001000010010 "
b101001000010010 M
b101001000010010 0
b1111111111111111111111111111111110110010110000101000010001100101 L
b1111111111111111111111111111111110110010110000101000010001100101 /
b10100100011111 4
b1000010001100101 3
b1111111111111111 D
b1111111111111111 >
b1011001011000010 8
b1000010001100101 O
b1111111111111111 [
b1111111111111111 W
b1011001011000010 S
b10100100011111 Q
b1101011001110111 4
b1101111000110 F
b1101111000110 @
b101000001000010 :
b1110010000111001111001000011100111100100001110010010100100011111 1
b10100100011111 6
b10100100011111 9
b1110010000111001111001000011100111100100001110010010100100011111 N
b101000001000010 U
b1101111000110 Y
b1101111000110 \
b10100100011111 R
b1101011001110111 Q
b1001101111011101 :
b1110010000111001111001000011100111100100001110010010100100011111 $
b1110010000111001111001000011100111100100001110010010100100011111 %
b1110010000111001111001000011100101010000010000100010100100011111 1
b1110010000111001000110111100011001010000010000100010100100011111 1
b1101111000110000110111100011001010000010000100010100100011111 1
b1101111000110000110111100011001010000010000101101011001110111 1
b1101011001110111 6
b101000001000010 <
b1101111000110 B
b1101111000110 E
b101000001000010 ?
b1101011001110111 9
b1101011001110111 R
b1001101111011101 U
b1101111000110 Z
b1101111000110000110111100011001010000010000101101011001110111 N
b101000001000010 V
b1110010000111001 F
b1010111110111101 @
b110010010110101 :
b1101111000110000110111100011001010000010000101101011001110111 %
b1101111000110000110111100011001010000010000101101011001110111 $
b1101111000110000110111100011010011011110111011101011001110111 1
b1001101111011101 <
b1001101111011101 ?
b1010111110111101 Y
b1110010000111001 \
b1101111000110000110111100011010011011110111011101011001110111 N
b1001101111011101 V
b110010010110101 U
b110010000100010 @
b1101111000110000110111100011010011011110111011101011001110111 %
b1101111000110000110111100011010011011110111011101011001110111 $
b1101111000110000110111100011001100100101101011101011001110111 1
b1101111000110101011111011110101100100101101011101011001110111 1
b1110010000111001101011111011110101100100101101011101011001110111 1
b110010010110101 <
b1010111110111101 B
b1010111110111101 E
b110010010110101 ?
b110010010110101 V
b110010000100010 Y
b1110010000111001101011111011110101100100101101011101011001110111 N
b1010111110111101 Z
b101000001000010 F
b1001101101001010 @
b1110010000111001101011111011110101100100101101011101011001110111 %
b1110010000111001101011111011110101100100101101011101011001110111 $
b1110010000111001011001000010001001100100101101011101011001110111 1
b110010000100010 B
b110010000100010 E
b101000001000010 \
b1110010000111001011001000010001001100100101101011101011001110111 N
b110010000100010 Z
b1001101101001010 Y
b1001101111011101 F
b1110010000111001011001000010001001100100101101011101011001110111 %
b1110010000111001011001000010001001100100101101011101011001110111 $
b1110010000111001100110110100101001100100101101011101011001110111 1
b101000001000010100110110100101001100100101101011101011001110111 1
b1001101101001010 B
b1001101101001010 E
b1001101101001010 Z
b1001101111011101 \
b101000001000010100110110100101001100100101101011101011001110111 N
b110010010110101 F
b101000001000010100110110100101001100100101101011101011001110111 %
b101000001000010100110110100101001100100101101011101011001110111 $
b1001101111011101100110110100101001100100101101011101011001110111 1
b1001101111011101100110110100101001100100101101011101011001110111 N
b110010010110101 \
b1001101111011101100110110100101001100100101101011101011001110111 %
b1001101111011101100110110100101001100100101101011101011001110111 $
b110010010110101100110110100101001100100101101011101011001110111 1
b110010010110101100110110100101001100100101101011101011001110111 N
b110010010110101100110110100101001100100101101011101011001110111 %
b110010010110101100110110100101001100100101101011101011001110111 $
#3960000
0&
#4015000
1&
#4070000
0&
#4125000
1&
#4180000
0&
#4235000
1&
#4290000
0&
#4345000
1&
#4400000
0&
#4455000
1&
