ex05/Programming_Task_0/status_module.sv
import fourteen_segment_display::*;
module seg_display(
  input logic  [7 : 0] data_i,
  input logic rst_ni,
  input logic clk_i,
  output logic [14:0] fourteen_seg_out
);

typedef enum {
    RESET,
    OKAY,
    COLD,
    WARM,
    TOO_COLD,
    TOO_WARM
} state_t;

state_t current_state, next_state; 


// State transitions on positive clock edge and reset
always_ff @(posedge clk_i or negedge rst_ni) begin
    if(!rst_ni) begin
        current_state <= RESET;
    end else begin
        current_state <= next_state;
    end
end

always_comb begin
    case(current_state)
      COLD: begin
        fourteen_seg_out = C;
      end
      WARM: begin
        fourteen_seg_out = W;
      end
      OKAY: begin
        fourteen_seg_out = O;
      end
      TOO_COLD: begin
        fourteen_seg_out = C_dot;
      end
      TOO_WARM: begin
        fourteen_seg_out = W_dot;
      end
      default: begin
        fourteen_seg_out = R;
      end
    endcase
end

// State transitions
always_comb begin
    case (current_state) inside
        RESET, OKAY: begin
            if($signed(data_i) <= -16) begin
                next_state = COLD;
            end else if($signed(data_i) > 45) begin
                next_state = WARM;
            end else begin
                next_state = OKAY;
            end
        end
        COLD: begin
            // Additional case <-45° (check first!)
            if($signed(data_i) < -45) begin
                next_state = TOO_COLD;
            end else if($signed(data_i) <= -16) begin
                next_state = COLD;
            end else if($signed(data_i) > 45) begin
                next_state = WARM;
            end else begin
                next_state = OKAY;
            end
        end
        WARM: begin
            // Additional case >60° (check first!)
            if($signed(data_i) > 60) begin
                next_state = TOO_WARM;
            end else if($signed(data_i) <= -16) begin
                next_state = COLD;
            end else if($signed(data_i) > 45) begin
                next_state = WARM;
            end else begin
                next_state = OKAY;
            end
        end
        TOO_WARM: begin
            next_state = RESET;
        end
        TOO_COLD: begin
            next_state = RESET;
        end
        default: begin
            next_state = RESET;
        end
    endcase
end

endmodule

ex05/Programming_Task_0/tb_status_module.sv
import fourteen_segment_display::*;
module tb_status_module;

logic  [7 : 0] temperature;
logic rst_ni;
logic clk_i;
logic [14:0] fourteen_seg_out;

seg_display status_mod (
    .data_i(temperature),
    .rst_ni(rst_ni),
    .clk_i(clk_i),
    .fourteen_seg_out(fourteen_seg_out)
);


// We go for a manual clock to better control it here before deciding to do it differently in the other tasks
initial begin

    // #### START-1: Single-State Transitions from Reset ####
    rst_ni = 'b1;
    #(5ns)

    // R -> C
    rst_ni = 'b0;
    #(1ns);
    rst_ni = 'b1;
    clk_i = 'b0;
    temperature = -16;
    #(1ns);
    clk_i = ~clk_i;
    #(1ns);
    reset_to_cold: assert (fourteen_seg_out == C);

    // R -> O
    rst_ni = 'b0;
    #(1ns);
    rst_ni = 'b1;
    clk_i = 'b0;
    temperature = -15;
    #(1ns);
    clk_i = ~clk_i;
    #(1ns);
    reset_to_okay_lower_bound: assert (fourteen_seg_out == O);

    rst_ni = 'b0;
    #(1ns);
    rst_ni = 'b1;
    clk_i = 'b0;
    temperature = 45;
    #(1ns);
    clk_i = ~clk_i;
    #(1ns);
    reset_to_okay_upper_bound: assert (fourteen_seg_out == O);

     // R -> W
    rst_ni = 'b0;
    #(1ns);
    rst_ni = 'b1;
    clk_i = 'b0;
    temperature = 46;
    #(1ns);
    clk_i = ~clk_i;
    #(1ns);
    reset_to_warm: assert (fourteen_seg_out == W);

    // #### END-1 ####



    // #### START-2: Transitions from start into too hot / too cold with reset following ####

    // R -> C -> C. -> R
    rst_ni = 'b0;
    #(1ns);
    rst_ni = 'b1;
    clk_i = 'b0;
    temperature = -60;
    #(1ns);
    clk_i = ~clk_i;
    #(1ns);
    reset_to_cold2: assert (fourteen_seg_out == C);
    clk_i = ~clk_i; // 1 -> 0
    #(1ns);
    clk_i = ~clk_i; // 0 -> 1
    #(1ns);
    too_cold: assert (fourteen_seg_out == C_dot)
    clk_i = ~clk_i; // 1 -> 0
    #(1ns);
    clk_i = ~clk_i; // 0 -> 1
    #(1ns);
    reset_after_too_cold: assert (fourteen_seg_out == R);


     // R -> W -> W. -> R
    rst_ni = 'b0;
    #(1ns);
    rst_ni = 'b1;
    clk_i = 'b0;
    temperature = 61;
    #(1ns);
    clk_i = ~clk_i;
    #(1ns);
    reset_to_warm2: assert (fourteen_seg_out == W);
    clk_i = ~clk_i; // 1 -> 0
    #(1ns);
    clk_i = ~clk_i; // 0 -> 1
    #(1ns);
    too_warm: assert (fourteen_seg_out == W_dot)
    clk_i = ~clk_i; // 1 -> 0
    #(1ns);
    clk_i = ~clk_i; // 0 -> 1
    #(1ns);
    reset_after_too_warm: assert (fourteen_seg_out == R);

    // #### END-2 ####


    // START-3: From (COLD, WARM, OKAY) to (COLD, WARM, OKAY) (some tests)

    rst_ni = 'b0;
    #(1ns);
    rst_ni = 'b1;
    clk_i = 'b0;
    temperature = 15;
    #(1ns);
    clk_i = ~clk_i; // 0 -> 1
    #(1ns);
    clk_i = ~clk_i; // 0 -> 1
    #(1ns);
    stay_okay: assert (fourteen_seg_out == O);


    // (OKAY) -> (WARM); (stay in warm); (WARM) -> (OKAY)
    clk_i = ~clk_i; // 1 -> 0
    temperature = 50;
    #(1ns);
    clk_i = ~clk_i; // 0 -> 1
    #(1ns);
    okay_to_warm: assert (fourteen_seg_out == W);
    clk_i = ~clk_i; // 1 -> 0
    temperature = 47;
    #(1ns);
    clk_i = ~clk_i; // 0 -> 1
    #(1ns);
    stay_warm: assert (fourteen_seg_out == W);
    clk_i = ~clk_i; // 1 -> 0
    temperature = 20;
    #(1ns);
    clk_i = ~clk_i; // 0 -> 1
    #(1ns);
    warm_to_okay: assert (fourteen_seg_out == O);

    // (OKAY) -> (COLD); (stay cold); (COLD) -> (WARM); (WARM) -> (COLD); (COLD) -> (OKAY)
    clk_i = ~clk_i; // 1 -> 0
    temperature = -30;
    #(1ns);
    clk_i = ~clk_i; // 0 -> 1
    #(1ns);
    okay_to_cold: assert (fourteen_seg_out == C);
    clk_i = ~clk_i; // 1 -> 0
    temperature = -31;
    #(1ns);
    clk_i = ~clk_i; // 0 -> 1
    #(1ns);
    stay_cold: assert (fourteen_seg_out == C);
    temperature = 100;
    #(1ns);
    clk_i = ~clk_i; // 0 -> 1
    #(1ns);
    cold_to_warm: assert (fourteen_seg_out == W);
    clk_i = ~clk_i; // 1 -> 0
    temperature = -20;
    #(1ns);
    clk_i = ~clk_i; // 0 -> 1
    #(1ns);
    warm_to_cold: assert (fourteen_seg_out == C);
    clk_i = ~clk_i; // 1 -> 0
    temperature = 0;
    #(1ns);
    clk_i = ~clk_i; // 0 -> 1
    #(1ns);
    cold_to_okay: assert (fourteen_seg_out == O);

    // #### END-3 ####

    
    
    // #### START-4 Make sure the asynchronous reset is asynchronous ####
    rst_ni = 'b0;
    #(1ns);
    reset: assert (fourteen_seg_out == R);
    #(1ns);
    // #### END-4 ####
    

end

endmodule

ex05/vcd_files/status_module.vcd
$date
    Jun  8, 2025  15:34:33
$end
$comment
	SimVision SST: d37fa0eb34ee6115b71f12b7fe0b461f
$end
$version
    TOOL:	xmsim(64)	22.09-s007
$end
$timescale
    1 fs
$end

$scope module tb_status_module $end
$var reg       8 !    temperature [7:0] $end
$var reg       1 "    rst_ni $end
$var reg       1 #    clk_i $end
$var reg      15 $    fourteen_seg_out [14:0] $end

$scope module status_mod $end
$var wire      8 %    data_i [7:0] $end
$var wire      1 &    rst_ni  $end
$var wire      1 '    clk_i  $end
$var reg      15 (    fourteen_seg_out [14:0] $end
$var reg      32 )    current_state [31:0] $end
$var reg      32 *    next_state [31:0] $end
$upscope $end

$upscope $end

$enddefinitions $end
$dumpvars
bx !
1"
x#
b1110001001101 $
bx %
1&
x'
b1110001001101 (
b0 )
b1 *
$end
#5000000
0"
0&
#6000000
1"
0#
b11110000 !
b11110000 %
0'
1&
b10 *
#7000000
1#
1'
b10 )
b1010100000001 (
b1010100000001 $
#8000000
0"
0&
b0 )
b1110001001101 (
b1110001001101 $
#9000000
1"
0#
b11110001 !
b11110001 %
0'
1&
b1 *
#10000000
1#
1'
b1 )
b1010100010101 (
b1010100010101 $
#11000000
0"
0&
b0 )
b1110001001101 (
b1110001001101 $
#12000000
1"
0#
b101101 !
b101101 %
0'
1&
#13000000
1#
1'
b1 )
b1010100010101 (
b1010100010101 $
#14000000
0"
0&
b0 )
b1110001001101 (
b1110001001101 $
#15000000
1"
0#
b101110 !
b101110 %
0'
1&
b11 *
#16000000
1#
1'
b11 )
b1011001010100 (
b1011001010100 $
#17000000
0"
0&
b0 )
b1110001001101 (
b1110001001101 $
#18000000
1"
0#
b11000100 !
b11000100 %
0'
1&
b10 *
#19000000
1#
1'
b10 )
b1010100000001 (
b100 *
b1010100000001 $
#20000000
0#
0'
#21000000
1#
1'
b100 )
b1010100100001 (
b0 *
b1010100100001 $
#22000000
0#
0'
#23000000
1#
1'
b0 )
b1110001001101 (
b10 *
b1110001001101 $
#24000000
0"
0&
#25000000
1"
0#
b111101 !
b111101 %
0'
1&
b11 *
#26000000
1#
1'
b11 )
b1011001010100 (
b101 *
b1011001010100 $
#27000000
0#
0'
#28000000
1#
1'
b101 )
b1011001110100 (
b0 *
b1011001110100 $
#29000000
0#
0'
#30000000
1#
1'
b0 )
b1110001001101 (
b11 *
b1110001001101 $
#31000000
0"
0&
#32000000
1"
0#
b1111 !
b1111 %
0'
1&
b1 *
#33000000
1#
1'
b1 )
b1010100010101 (
b1010100010101 $
#34000000
0#
0'
#35000000
1#
b110010 !
b110010 %
1'
b11 *
b11 )
b1011001010100 (
b1011001010100 $
#36000000
0#
0'
#37000000
1#
b101111 !
b101111 %
1'
#38000000
0#
0'
#39000000
1#
b10100 !
b10100 %
1'
b1 *
b1 )
b1010100010101 (
b1010100010101 $
#40000000
0#
0'
#41000000
1#
b11100010 !
b11100010 %
1'
b10 *
b10 )
b1010100000001 (
b1010100000001 $
#42000000
0#
0'
#43000000
1#
b11100001 !
b11100001 %
1'
#44000000
0#
0'
#45000000
b1100100 !
b1100100 %
b11 *
#46000000
1#
1'
b11 )
b1011001010100 (
b101 *
b1011001010100 $
#47000000
0#
b11101100 !
b11101100 %
0'
b10 *
#48000000
1#
1'
b10 )
b1010100000001 (
b1010100000001 $
#49000000
0#
b0 !
b0 %
0'
b1 *
#50000000
1#
1'
b1 )
b1010100010101 (
b1010100010101 $
#51000000
0"
0&
b0 )
b1110001001101 (
b1110001001101 $
