ex05/Programming_Task_1/moving_average.sv
module avg(
    input logic rst_ni,
    input logic clk_i,
    input logic  [7:0] temperature,
    output logic [7:0] data_o
);

// In this task, you will create a small process pipeline that reads the temperature from a model of an 8-bit signed
// temperature sensor, calculates the average of the last three measurements and passes this to a status process. The
// model of the temperature sensor outputs a new random temperature value each time the sample_in signal changes.
// The status process reacts to the measured temperature and outputs it on a 14-segment display (14SA) 1 . An overview
// of the pipeline can be seen in Figure 1.

logic [7:0] measurement_previous;
logic [7:0] measurement_pre_previous;

// What results if no average can be calculated (first three values?)
always_ff @(posedge clk_i or negedge rst_ni) begin
    if(!rst_ni) begin
        // It makes sense to reset to the currently measured temperature instead of 0 bc it may immediately get read out
        // In testing though we should still wait 3 cycles after reset always
        measurement_previous     <= temperature;
        measurement_pre_previous <= temperature;
        data_o <= temperature;
    end else begin
        data_o <= (temperature + measurement_previous + measurement_pre_previous) / 3;
        measurement_previous     <= temperature;
        measurement_pre_previous <= measurement_previous;
    end
end

endmodule

ex05/Programming_Task_3/process_communication/tb_synthesized.sv
module tb_moving_average;

logic clock_in;
logic reset_n_in;
logic [7 : 0] temperature;
logic [7 : 0] temperature_average;

avg u_avg (
    .rst_ni         (reset_n_in),
    .clk_i          (clock_in),
    .temperature    (temperature),
    .data_o         (temperature_average)
);

always #(5ns) clock_in = ~clock_in;


initial begin

    temperature = 10;

    reset_n_in = 'b0;
    clock_in   = 'b0;

    #(10ns)
    reset_n_in = 'b1;
    #(1ns);
    val1: assert ($signed(temperature_average) == 10);

    temperature = 50;
    #(5ns);
    val2: assert ($signed(temperature_average) == 23);

    temperature = -27;
    #(10ns);
    val3: assert ($signed(temperature_average) == 11);

    temperature = -32;
    #(10ns);
    val4: assert ($signed(temperature_average) == -3);

    // Dont change value from -36, see if average settles
    #(10ns);
    val5: assert ($signed(temperature_average) == -30);

    #(10ns);
    val6: assert ($signed(temperature_average) == -32);

    // Change temperature inside clock cycle, it should not do anything except the one set to before rising edge
    temperature = 90;
    #(6ns);
    nochange1: assert ($signed(temperature_average) == -32)
    temperature = 50;
    #(2ns);
    nochange2: assert ($signed(temperature_average) == -32)
    temperature = 0;
    #(2ns) // This goes over the rising clock edge
    val7: assert ($signed(temperature_average) == -21)

    #(10ns)
    val8: assert ($signed(temperature_average) == -10)

    temperature = 90;
    #(10ns)
    val9: assert ($signed(temperature_average) == 30);

    temperature = -30;
    #(10ns)
    val10: assert ($signed(temperature_average) == 20);

    temperature = 6;
    #(10ns)
    val11: assert ($signed(temperature_average) == 22);

    // Multiple cycles to settle on 6, then:
    // A somewhat realistic variation of +-2 around the actual value of 6 -> still fluctuating a lot with just 3 average values
    #(30ns)
    temperature = 5;
    #(10ns)
    val12:assert ($signed(temperature_average) == 5);

    temperature = 6;
    #(10ns)
    val13: assert ($signed(temperature_average) == 5);

    temperature = 7;
    #(10ns)
    val14: assert ($signed(temperature_average) == 6);

    temperature = 8;
    #(10ns)
    val15: assert ($signed(temperature_average) == 7);

    temperature = 5;
    #(10ns)
    val16: assert ($signed(temperature_average) == 6);


    $finish;

end

endmodule

ex05/vcd_files/tb_moving_average.vcd
$date
    Jun  8, 2025  15:37:18
$end
$comment
	SimVision SST: d37fa0eb34ee6115b71f12b7fe0b461f
$end
$version
    TOOL:	xmsim(64)	22.09-s007
$end
$timescale
    1 fs
$end

$scope module tb_moving_average $end
$var reg       1 !    clock_in $end
$var reg       1 "    reset_n_in $end
$var reg       8 #    temperature [7:0] $end
$var reg       8 $    temperature_average [7:0] $end

$scope module u_avg $end
$var wire      1 %    rst_ni  $end
$var wire      1 &    clk_i  $end
$var wire      8 '    temperature [7:0] $end
$var reg       8 (    data_o [7:0] $end
$var reg       8 )    measurement_previous [7:0] $end
$var reg       8 *    measurement_pre_previous [7:0] $end
$upscope $end

$upscope $end

$enddefinitions $end
$dumpvars
0!
0"
b1010 #
b1010 $
0%
0&
b1010 '
b1010 (
b1010 )
b1010 *
$end
#5000000
1!
1&
#10000000
1"
0!
0&
1%
#11000000
b110010 #
b110010 '
#15000000
1!
1&
b10111 (
b110010 )
b10111 $
#16000000
b11100101 #
b11100101 '
#20000000
0!
0&
#25000000
1!
1&
b1011 (
b11100101 )
b110010 *
b1011 $
#26000000
b11100000 #
b11100000 '
#30000000
0!
0&
#35000000
1!
1&
b11111101 (
b11100000 )
b11100101 *
b11111101 $
#40000000
0!
0&
#45000000
1!
1&
b11100010 (
b11100000 *
b11100010 $
#50000000
0!
0&
#55000000
1!
1&
b11100000 (
b11100000 $
#56000000
b1011010 #
b1011010 '
#60000000
0!
0&
#62000000
b110010 #
b110010 '
#64000000
b0 #
b0 '
#65000000
1!
1&
b11101011 (
b0 )
b11101011 $
#70000000
0!
0&
#75000000
1!
1&
b11110110 (
b0 *
b11110110 $
#76000000
b1011010 #
b1011010 '
#80000000
0!
0&
#85000000
1!
1&
b11110 (
b1011010 )
b11110 $
#86000000
b11100010 #
b11100010 '
#90000000
0!
0&
#95000000
1!
1&
b10100 (
b11100010 )
b1011010 *
b10100 $
#96000000
b110 #
b110 '
#100000000
0!
0&
#105000000
1!
1&
b10110 (
b110 )
b11100010 *
b10110 $
#110000000
0!
0&
#115000000
1!
1&
b11111010 (
b110 *
b11111010 $
#120000000
0!
0&
#125000000
1!
1&
b110 (
b110 $
#130000000
0!
0&
#135000000
1!
1&
#136000000
b101 #
b101 '
#140000000
0!
0&
#145000000
1!
1&
b101 (
b101 )
b101 $
#146000000
b110 #
b110 '
#150000000
0!
0&
#155000000
1!
1&
b110 )
b101 *
#156000000
b111 #
b111 '
#160000000
0!
0&
#165000000
1!
1&
b110 (
b111 )
b110 *
b110 $
#166000000
b1000 #
b1000 '
#170000000
0!
0&
#175000000
1!
1&
b111 (
b1000 )
b111 *
b111 $
#176000000
b101 #
b101 '
#180000000
0!
0&
#185000000
1!
1&
b110 (
b101 )
b1000 *
b110 $
